setup.py
distrib_bertrand/Binomialdistribution.py
distrib_bertrand/Gaussiandistribution.py
distrib_bertrand/Generaldistribution.py
distrib_bertrand/__init__.py
distrib_bertrand.egg-info/PKG-INFO
distrib_bertrand.egg-info/SOURCES.txt
distrib_bertrand.egg-info/dependency_links.txt
distrib_bertrand.egg-info/not-zip-safe
distrib_bertrand.egg-info/top_level.txt