Metadata-Version: 1.0
Name: distrib-bertrand
Version: 0.1
Summary: Gaussian distributions of Bertrand
Home-page: UNKNOWN
Author: Bertrand
Author-email: mctchuente@gmail.com
License: UNKNOWN
Platform: UNKNOWN
